langchain_cli/__init__.py
langchain_cli/main.py
langchain_cli/scaffolding.py
langchain_cli/commands/__init__.py
langchain_cli/commands/tools.py
langchain_cli/templates/toolkit/client_example.py.j2
langchain_cli/templates/toolkit/pyproject.toml.j2
langchain_cli/templates/toolkit/toolkit.toml.j2
langchain_cli/templates/toolkit/package_name/__init__.py.j2
langchain_cli/templates/toolkit/package_name/auth.py.j2
langchain_cli/templates/toolkit/package_name/tools/__init__.py.j2
langchain_cli/templates/toolkit/package_name/tools/math.py.j2
langchain_cli/templates/toolkit/package_name/tools/text.py.j2
langchain_cli_v2-0.1.11.dist-info/METADATA
langchain_cli_v2-0.1.11.dist-info/WHEEL
langchain_cli_v2-0.1.11.dist-info/entry_points.txt
langchain_cli_v2-0.1.11.dist-info/top_level.txt
langchain_cli_v2-0.1.11.dist-info/RECORD
